horde_client/__init__.py
horde_client/async_client.py
horde_client/client.py
horde_client/config.py
horde_client/errors.py
horde_client/langchain_llm.py
horde_client/model.py
horde_client/utility.py
horde_client-1.0.3.dist-info/LICENSE
horde_client-1.0.3.dist-info/METADATA
horde_client-1.0.3.dist-info/WHEEL
horde_client-1.0.3.dist-info/top_level.txt
horde_client-1.0.3.dist-info/RECORD
