Metadata-Version: 2.1
Name: horde-client
Version: 1.0.3
Summary: Python Interface for AIHorde
Home-page: https://github.com/rahuldshetty/horde-client.git
Author: Rahul D Shettu
Author-email: 35rahuldshetty@gmail.com
License-File: LICENSE
Requires-Dist: requests ==2.27.1
Requires-Dist: pydantic ==2.3.0
Requires-Dist: asyncio-requests ==2.7.3
Requires-Dist: langchain ==0.0.291
